lcd_st7032/__init__.py
lcd_st7032/lcd_7032.py
lcd_st7032-0.2.0.dist-info/METADATA
lcd_st7032-0.2.0.dist-info/RECORD
lcd_st7032-0.2.0.dist-info/WHEEL
lcd_st7032-0.2.0.dist-info/top_level.txt
